AUTHORS
LICENSE
MANIFEST.in
README.rst
requirements.txt
setup.py
docs/Makefile
docs/conf.py
docs/index.rst
nashvegas/__init__.py
nashvegas/admin.py
nashvegas/models.py
nashvegas/tests.py
nashvegas/utils.py
nashvegas.egg-info/PKG-INFO
nashvegas.egg-info/SOURCES.txt
nashvegas.egg-info/dependency_links.txt
nashvegas.egg-info/not-zip-safe
nashvegas.egg-info/top_level.txt
nashvegas/management/__init__.py
nashvegas/management/commands/__init__.py
nashvegas/management/commands/comparedb.py
nashvegas/management/commands/syncdb.py
nashvegas/management/commands/upgradedb.py