Metadata-Version: 1.0
Name: nashvegas
Version: 0.7
Summary: nashvegas is a management command for managing Django database migrations
Home-page: http://github.com/paltman/nashvegas/
Author: Patrick Altman
Author-email: paltman@gmail.com
License: UNKNOWN
Platform: UNKNOWN
Classifier: Development Status :: 4 - Beta
Classifier: Environment :: Web Environment
Classifier: Intended Audience :: Developers
Classifier: License :: OSI Approved :: MIT License
Classifier: Operating System :: OS Independent
Classifier: Framework :: Django
Classifier: Programming Language :: Python
Classifier: Programming Language :: Python :: 2.5
